<xml xmlns="http://www.w3.org/1999/xhtml">
  <variables>
    <variable type="" id="#?%Pl{y-9/4a(!(-822;">score</variable>
    <variable type="Actor" id="LaDF,Ghir0.%{o^~CJo:">hero</variable>
    <variable type="Actor" id="S[@RD!]6,.F!H^2rZ!{d">block</variable>
    <variable type="Actor" id="`v#rKH?.b_KL|*Rc9k?T">gagne</variable>
  </variables>
  <block type="game_create" id="G-Yt.VdBA/p,$6z:@1fx" x="-5150" y="-650">
    <field name="IMG">tile_1</field>
    <field name="WIDTH">800</field>
    <field name="HEIGHT">600</field>
    <next>
      <block type="variables_set" id="BGLDGXL(=bL@JR4!#f|S" inline="true">
        <field name="VAR" id="#?%Pl{y-9/4a(!(-822;" variabletype="">score</field>
        <value name="VALUE">
          <shadow type="logic_null" id="IrIp$Py=bA?f$,tZ+AcZ"></shadow>
          <block type="math_number" id="JZS9,wR-kKAm21xB}L!W" inline="true">
            <field name="NUM">0</field>
          </block>
        </value>
        <next>
          <block type="text_add_text" id="^yX?FqRJm-ZL=Q!90g-j">
            <field name="PROPERTY">TOP_LEFT</field>
            <value name="TEXT">
              <shadow type="text" id="FwW!m#%Jg.@h{9;Y/vR#">
                <field name="TEXT">abc</field>
              </shadow>
              <block type="variables_get" id="??.rW9p*VzLt2):}MCOj">
                <field name="VAR" id="#?%Pl{y-9/4a(!(-822;" variabletype="">score</field>
              </block>
            </value>
            <next>
              <block type="actor_create" id="Wh?BHH$b,?sEsV}uT~x+">
                <field name="ACTOR" id="LaDF,Ghir0.%{o^~CJo:" variabletype="Actor">hero</field>
                <value name="IMG">
                  <shadow type="images_planetcute" id="puaQ}Lw/Af6R#bVh[ZHC">
                    <field name="VALUE">Character Horn Girl</field>
                  </shadow>
                </value>
                <value name="X">
                  <shadow type="math_number" id="TD1Cgm%1u2_$j7zW_JcF">
                    <field name="NUM">100</field>
                  </shadow>
                </value>
                <value name="Y">
                  <shadow type="math_number" id="v3_QptUVj5/PmBE-dE@f">
                    <field name="NUM">100</field>
                  </shadow>
                </value>
                <next>
                  <block type="actor_method_0" id="R.7)ryath{k;Wd1Iv$I$">
                    <field name="ACTOR" id="LaDF,Ghir0.%{o^~CJo:" variabletype="Actor">hero</field>
                    <field name="METHOD">setFixedRotation</field>
                    <next>
                      <block type="event_create" id="xD^qb%?mmHbFV~]O}|ks">
                        <value name="EVENT">
                          <block type="event_scene_key" id="}2*o{KYm[6p)S]}sDA;t">
                            <field name="EVENT">ON</field>
                            <field name="KEY">38</field>
                          </block>
                        </value>
                        <statement name="STMT">
                          <block type="actor_method_1" id="!qVuCq!TVv`kuU`26riI">
                            <field name="ACTOR" id="LaDF,Ghir0.%{o^~CJo:" variabletype="Actor">hero</field>
                            <field name="METHOD">jump</field>
                            <value name="VALUE">
                              <shadow type="math_number" id="/[jEK{sRG+Y$V-!Zd%W@">
                                <field name="NUM">10</field>
                              </shadow>
                            </value>
                          </block>
                        </statement>
                        <next>
                          <block type="event_create" id="LB`Pyf7plqoHCuGKcjj_">
                            <value name="EVENT">
                              <block type="event_scene_key" id="TSQ;wgO|7i%dWUl?25Xy">
                                <field name="EVENT">ON</field>
                                <field name="KEY">39</field>
                              </block>
                            </value>
                            <statement name="STMT">
                              <block type="actor_set" id="67fjok3+xp/mf2xJ*nTB">
                                <field name="ACTOR" id="LaDF,Ghir0.%{o^~CJo:" variabletype="Actor">hero</field>
                                <field name="PROPERTY">posX</field>
                                <value name="VALUE">
                                  <shadow type="math_number" id=":E(-T%.xKeR5$k^%=`}]">
                                    <field name="NUM">100</field>
                                  </shadow>
                                  <block type="math_arithmetic" id="~sUFEchF!$=;7uF^xXLN">
                                    <field name="OP">ADD</field>
                                    <value name="A">
                                      <shadow type="math_number" id="2h]CBkWNwG6sKU^lpIq`">
                                        <field name="NUM">1</field>
                                      </shadow>
                                      <block type="actor_get" id="xA]QW6jWvowYClGk.gkY">
                                        <field name="ACTOR" id="LaDF,Ghir0.%{o^~CJo:" variabletype="Actor">hero</field>
                                        <field name="PROPERTY">posX</field>
                                      </block>
                                    </value>
                                    <value name="B">
                                      <shadow type="math_number" id="sDF-fISqxsj])`8)_:$5">
                                        <field name="NUM">80</field>
                                      </shadow>
                                    </value>
                                  </block>
                                </value>
                              </block>
                            </statement>
                            <next>
                              <block type="event_create" id="D7GJlQpH{gwG(*7~N^ps">
                                <value name="EVENT">
                                  <block type="event_scene_key" id="k(NigWMCs%D%ev#Mbt4t">
                                    <field name="EVENT">ON</field>
                                    <field name="KEY">37</field>
                                  </block>
                                </value>
                                <statement name="STMT">
                                  <block type="actor_set" id="b+/y!-//nLqT%uv2;`C,">
                                    <field name="ACTOR" id="LaDF,Ghir0.%{o^~CJo:" variabletype="Actor">hero</field>
                                    <field name="PROPERTY">posX</field>
                                    <value name="VALUE">
                                      <shadow type="math_number" id="8]w9A{W4h=M8ex)w^rIF">
                                        <field name="NUM">100</field>
                                      </shadow>
                                      <block type="math_arithmetic" id="D]reX]WYojJ0}t!hkNTY">
                                        <field name="OP">MINUS</field>
                                        <value name="A">
                                          <shadow type="math_number" id="2Yv0D}c$VWcqIMatR_0~">
                                            <field name="NUM">1</field>
                                          </shadow>
                                          <block type="actor_get" id="KgQ.Hd_[8[dPyyu`(D3}">
                                            <field name="ACTOR" id="LaDF,Ghir0.%{o^~CJo:" variabletype="Actor">hero</field>
                                            <field name="PROPERTY">posX</field>
                                          </block>
                                        </value>
                                        <value name="B">
                                          <shadow type="math_number" id="{iQ4CEeOt-*d$tw7vUzg">
                                            <field name="NUM">80</field>
                                          </shadow>
                                        </value>
                                      </block>
                                    </value>
                                  </block>
                                </statement>
                                <next>
                                  <block type="actor_create" id="w;6vu.j*IDW}at(C,L{s">
                                    <field name="ACTOR" id="S[@RD!]6,.F!H^2rZ!{d" variabletype="Actor">block</field>
                                    <value name="IMG">
                                      <shadow type="images_planetcute" id="r!`PE#Qpak1Set(Olk^[">
                                        <field name="VALUE">Dirt Block</field>
                                      </shadow>
                                    </value>
                                    <value name="X">
                                      <shadow type="math_number" id="CA~DopuizWS42Z4xND(l">
                                        <field name="NUM">400</field>
                                      </shadow>
                                    </value>
                                    <value name="Y">
                                      <shadow type="math_number" id=".e{5%50/rg^%`{#XDI#p">
                                        <field name="NUM">400</field>
                                      </shadow>
                                    </value>
                                    <next>
                                      <block type="actor_create" id="xgi[dt~L%U`6GR0,Lu,X">
                                        <field name="ACTOR" id="S[@RD!]6,.F!H^2rZ!{d" variabletype="Actor">block</field>
                                        <value name="IMG">
                                          <shadow type="images_planetcute" id="S?`=O-zdbaLmQ(^TkW]m">
                                            <field name="VALUE">Dirt Block</field>
                                          </shadow>
                                        </value>
                                        <value name="X">
                                          <shadow type="math_number" id="5S=*`S{M#wZ;M(tNxP[7">
                                            <field name="NUM">700</field>
                                          </shadow>
                                        </value>
                                        <value name="Y">
                                          <shadow type="math_number" id="p^%@_N(o+%FC7K8y]-i/">
                                            <field name="NUM">300</field>
                                          </shadow>
                                        </value>
                                        <next>
                                          <block type="actor_create" id="4XhX]:E7g~?K]y?KKP%T">
                                            <field name="ACTOR" id="S[@RD!]6,.F!H^2rZ!{d" variabletype="Actor">block</field>
                                            <value name="IMG">
                                              <shadow type="images_planetcute" id="NYgNX5sZi?DZyC`7Q2-L">
                                                <field name="VALUE">Dirt Block</field>
                                              </shadow>
                                            </value>
                                            <value name="X">
                                              <shadow type="math_number" id="Tp7h8j;PhIZeE6mj7NuQ">
                                                <field name="NUM">100</field>
                                              </shadow>
                                            </value>
                                            <value name="Y">
                                              <shadow type="math_number" id="gzPc@a,HbV!;%*P1NZY_">
                                                <field name="NUM">500</field>
                                              </shadow>
                                            </value>
                                            <next>
                                              <block type="actor_create" id="zZ(b[~Nh:7}!]21C*d2U">
                                                <field name="ACTOR" id="S[@RD!]6,.F!H^2rZ!{d" variabletype="Actor">block</field>
                                                <value name="IMG">
                                                  <shadow type="images_planetcute" id="}GIL3Ig/qj)=,|!|Bg`X">
                                                    <field name="VALUE">Dirt Block</field>
                                                  </shadow>
                                                </value>
                                                <value name="X">
                                                  <shadow type="math_number" id="$JF,{l.|_%j]~;4=Oq[0">
                                                    <field name="NUM">200</field>
                                                  </shadow>
                                                </value>
                                                <value name="Y">
                                                  <shadow type="math_number" id="kjPX}y1ubr|9nEXC^Gxz">
                                                    <field name="NUM">100</field>
                                                  </shadow>
                                                </value>
                                                <next>
                                                  <block type="actor_create" id="gq}ls]rWxSpECd^cug^!">
                                                    <field name="ACTOR" id="S[@RD!]6,.F!H^2rZ!{d" variabletype="Actor">block</field>
                                                    <value name="IMG">
                                                      <shadow type="images_planetcute" id="AVejd-,0S}d7TQ[`p@l)">
                                                        <field name="VALUE">Dirt Block</field>
                                                      </shadow>
                                                    </value>
                                                    <value name="X">
                                                      <shadow type="math_number" id="N/x#u:[CH6kooXHKhb!v">
                                                        <field name="NUM">300</field>
                                                      </shadow>
                                                    </value>
                                                    <value name="Y">
                                                      <shadow type="math_number" id="b-qL)6ip#3@Y_[/0JXCU">
                                                        <field name="NUM">250</field>
                                                      </shadow>
                                                    </value>
                                                    <next>
                                                      <block type="actor_create" id="i)vl,f/-W4(~QAu[Q_*P">
                                                        <field name="ACTOR" id="S[@RD!]6,.F!H^2rZ!{d" variabletype="Actor">block</field>
                                                        <value name="IMG">
                                                          <shadow type="images_planetcute" id="D{VDpyIsF`D[|FoZhIvP">
                                                            <field name="VALUE">Dirt Block</field>
                                                          </shadow>
                                                        </value>
                                                        <value name="X">
                                                          <shadow type="math_number" id="@7[mo_3syNEM16jNsO};">
                                                            <field name="NUM">600</field>
                                                          </shadow>
                                                        </value>
                                                        <value name="Y">
                                                          <shadow type="math_number" id="!hK4;/l;uJe8os_]mr,/">
                                                            <field name="NUM">550</field>
                                                          </shadow>
                                                        </value>
                                                        <next>
                                                          <block type="controls_repeat_ext" id="v1isls.Uhsw`j9L!;,85" inline="true">
                                                            <value name="TIMES">
                                                              <shadow type="math_number" id="ka,vqqoT`B=`iqe@q[KZ">
                                                                <field name="NUM">30</field>
                                                              </shadow>
                                                            </value>
                                                            <statement name="DO">
                                                              <block type="actor_create" id="|`}^PI=mlQ+;k^wxuf!u">
                                                                <field name="ACTOR" id="`v#rKH?.b_KL|*Rc9k?T" variabletype="Actor">gagne</field>
                                                                <value name="IMG">
                                                                  <shadow type="images_planetcute" id="|:L]zvkc]4k{j.8)0ur:">
                                                                    <field name="VALUE">Beetleship</field>
                                                                  </shadow>
                                                                  <block type="images_sport" id="u=*olH7h^HyXceEI?@hY">
                                                                    <field name="VALUE">HandYellow</field>
                                                                  </block>
                                                                </value>
                                                                <value name="X">
                                                                  <shadow type="math_number" id="1^0f{=z.m0S/%rsw1pku">
                                                                    <field name="NUM">700</field>
                                                                  </shadow>
                                                                </value>
                                                                <value name="Y">
                                                                  <shadow type="math_number" id="UvVEH-,vRuSq%S|i`ujp">
                                                                    <field name="NUM">296</field>
                                                                  </shadow>
                                                                </value>
                                                                <next>
                                                                  <block type="event_create" id="x2#|dDs[WsOzL)!fq(6:">
                                                                    <value name="EVENT">
                                                                      <block type="event_actor_collide" id="m|Uji5k`[h{Q%B/MXy|*">
                                                                        <field name="ACTOR" id="`v#rKH?.b_KL|*Rc9k?T" variabletype="Actor">gagne</field>
                                                                        <field name="EVENT">ON</field>
                                                                        <value name="IMG">
                                                                          <shadow type="images_planetcute" id="iQ|CsgWBVw|H7qxVEPUE">
                                                                            <field name="VALUE">Character Horn Girl</field>
                                                                          </shadow>
                                                                        </value>
                                                                      </block>
                                                                    </value>
                                                                    <statement name="STMT">
                                                                      <block type="variables_set" id="9ZAcg],RcwEJ(Py:i)yK" inline="true">
                                                                        <field name="VAR" id="#?%Pl{y-9/4a(!(-822;" variabletype="">score</field>
                                                                        <value name="VALUE">
                                                                          <shadow type="logic_null" id="LnY(9qkD2GWypMI*mgJ]"></shadow>
                                                                          <block type="math_arithmetic" id="`[ct,:c`(N*F4.A0H8O/">
                                                                            <field name="OP">ADD</field>
                                                                            <value name="A">
                                                                              <shadow type="math_number" id="#I2$r$QzhtAThy2@EzQ$">
                                                                                <field name="NUM">1</field>
                                                                              </shadow>
                                                                              <block type="variables_get" id="ibmo(Xv;CVx}SWfCnHqG">
                                                                                <field name="VAR" id="#?%Pl{y-9/4a(!(-822;" variabletype="">score</field>
                                                                              </block>
                                                                            </value>
                                                                            <value name="B">
                                                                              <shadow type="math_number" id="PQV,n[_4-]W9P*PVlG%t">
                                                                                <field name="NUM">1</field>
                                                                              </shadow>
                                                                            </value>
                                                                          </block>
                                                                        </value>
                                                                        <next>
                                                                          <block type="actor_method_0" id="CF#]GLf{]:l9Y5S$*=c=">
                                                                            <field name="ACTOR" id="`v#rKH?.b_KL|*Rc9k?T" variabletype="Actor">gagne</field>
                                                                            <field name="METHOD">destroy</field>
                                                                          </block>
                                                                        </next>
                                                                      </block>
                                                                    </statement>
                                                                    <next>
                                                                      <block type="sequence_wait" id="zKbciUby8BSF?)k:NXBR">
                                                                        <value name="TIME">
                                                                          <shadow type="math_number" id="~l`=wJDr[r)wB{dp^48m">
                                                                            <field name="NUM">0</field>
                                                                          </shadow>
                                                                        </value>
                                                                      </block>
                                                                    </next>
                                                                  </block>
                                                                </next>
                                                              </block>
                                                            </statement>
                                                          </block>
                                                        </next>
                                                      </block>
                                                    </next>
                                                  </block>
                                                </next>
                                              </block>
                                            </next>
                                          </block>
                                        </next>
                                      </block>
                                    </next>
                                  </block>
                                </next>
                              </block>
                            </next>
                          </block>
                        </next>
                      </block>
                    </next>
                  </block>
                </next>
              </block>
            </next>
          </block>
        </next>
      </block>
    </next>
  </block>
</xml>